assetmaker/__init__.py
assetmaker/assets.py
assetmaker-1.0.1.dist-info/METADATA
assetmaker-1.0.1.dist-info/WHEEL
assetmaker-1.0.1.dist-info/licenses/LICENCE
assetmaker-1.0.1.dist-info/RECORD
