Metadata-Version: 2.4
Name: assetmaker
Version: 1.0.1
Summary: A simple package to create assets for a project using json to store the data.
Project-URL: Documentation, https://github.com/Minecraft-Schools/assetmaker#readme
Project-URL: Issues, https://github.com/Minecraft-Schools/assetmaker/issues
Project-URL: Source, https://github.com/Minecraft-Schools/assetmaker
Author-email: WillDev <mcfakeypants.fakey@gmail.com>
License-Expression: MIT
License-File: LICENCE
Classifier: Development Status :: 4 - Beta
Classifier: Programming Language :: Python
Classifier: Programming Language :: Python :: 3.8
Classifier: Programming Language :: Python :: 3.9
Classifier: Programming Language :: Python :: 3.10
Classifier: Programming Language :: Python :: 3.11
Classifier: Programming Language :: Python :: 3.12
Requires-Python: >=3.8
